CommandPrompter/Command.py
CommandPrompter/Prompt_Result.py
CommandPrompter/Prompter.py
CommandPrompter/__init__.py
CommandPrompter/py.typed
commandprompter-0.1.0.dist-info/METADATA
commandprompter-0.1.0.dist-info/WHEEL
commandprompter-0.1.0.dist-info/top_level.txt
commandprompter-0.1.0.dist-info/RECORD
