Metadata-Version: 2.4
Name: CommandPrompter
Version: 0.1.0
Summary: Prompt Command or Message.
Author-email: scutiii2 <scuti.code@gmail.com>
License: MIT
